genapp/__init__.py
genapp/cli.py
genapp/script/__init__.py
genapp/script/clean_code.py
genapp/script/generator_.py
genapp/script/migrate_database.py
genapp/script/deploy/__init__.py
genapp/script/deploy/deploy.py
genapp/script/generator/__init__.py
genapp/script/generator/constants.py
genapp/script/generator/generator_dao.py
genapp/script/generator/generator_funtionalities.py
genapp/script/generator/generator_pydantic.py
genapp/script/generator/generator_system.py
genapp/script/generator/database/__init__.py
genapp/script/generator/database/oracle.py
genapp/script/generator/database/postgresql.py
genapp/script/generator/database/sqlserver.py
genapp/script/generator/database/connection/__init__.py
genapp/script/generator/database/connection/connection.py
genapp/script/generator/database/connection/connection_microsoft.py
genapp/script/generator/database/connection/connection_oracle.py
genapp/script/generator/database/connection/connection_postgres.py
genapp/script/generator/lib/__init__.py
genapp/script/generator/lib/sqlacodegen_v2/__init__.py
genapp/script/generator/lib/sqlacodegen_v2/external.py
genapp/script/generator/lib/sqlacodegen_v2/generators.py
genapp/script/generator/lib/sqlacodegen_v2/models.py
genapp/script/generator/lib/sqlacodegen_v2/utils.py
genapp/script/generator/schemas/__init__.py
genapp/script/generator/schemas/audit_file_schema.py
genapp/script/generator/schemas/authorization_file_schema.py
genapp/script/generator/schemas/cache_file_schema.py
genapp/script/generator/schemas/cache_listener_file_schema.py
genapp/script/generator/schemas/conn_file_schema.py
genapp/script/generator/schemas/connection_dao_file_schema.py
genapp/script/generator/schemas/funtionality_dao_file_schema.py
genapp/script/generator/schemas/login_dao_file_schema.py
genapp/script/generator/schemas/login_file_schema.py
genapp/script/generator/schemas/payload_file_schema.py
genapp/script/generator/schemas/role_dao_file_schema.py
genapp-0.1.11.dist-info/METADATA
genapp-0.1.11.dist-info/WHEEL
genapp-0.1.11.dist-info/entry_points.txt
genapp-0.1.11.dist-info/top_level.txt
genapp-0.1.11.dist-info/RECORD
