Metadata-Version: 2.1
Name: genapp
Version: 0.1.11
Summary: Genapp framework
Home-page: https://genapp.sytes.net/login
Author: ATL
Author-email: al.genericapp@gmail.com
Requires-Python: >=3.7
Requires-Dist: autopep8==2.1.0
Requires-Dist: absolufy-imports==0.3.1
Requires-Dist: annotated-types==0.6.0
Requires-Dist: anyio==4.3.0
Requires-Dist: aioodbc==0.5.0
Requires-Dist: aiosmtplib==3.0.2
Requires-Dist: async-timeout==4.0.3
Requires-Dist: asyncpg==0.29.0
Requires-Dist: cachetools==5.3.3
Requires-Dist: certifi==2024.2.2
Requires-Dist: click==8.1.7
Requires-Dist: colorama==0.4.6
Requires-Dist: cx-Oracle==8.3.0
Requires-Dist: device-detector==5.0.1
Requires-Dist: ecdsa==0.19.0
Requires-Dist: fastapi==0.110.1
Requires-Dist: firebase-admin==6.5.0
Requires-Dist: greenlet==3.0.3
Requires-Dist: h11==0.14.0
Requires-Dist: httpcore==1.0.5
Requires-Dist: httpx==0.27.0
Requires-Dist: idna==3.7
Requires-Dist: inflect==7.2.1
Requires-Dist: Jinja2==3.1.4
Requires-Dist: paho-mqtt==1.6.1
Requires-Dist: pandas==2.2.2
Requires-Dist: paramiko==3.4.0
Requires-Dist: plotly==5.22.0
Requires-Dist: psycopg2-binary==2.9.9
Requires-Dist: pyasn1==0.6.0
Requires-Dist: pydantic==2.7.0
Requires-Dist: pydantic-core==2.18.1
Requires-Dist: pyodbc==5.1.0
Requires-Dist: python-dotenv==1.0.1
Requires-Dist: python-jose==3.3.0
Requires-Dist: python-multipart==0.0.9
Requires-Dist: pytest==8.2.0
Requires-Dist: pytest-dotenv==0.5.2
Requires-Dist: pytest-tornasync==0.6.0
Requires-Dist: pytest-asyncio==0.23.6
Requires-Dist: PyYAML==6.0.1
Requires-Dist: regex==2023.12.25
Requires-Dist: rsa==4.9
Requires-Dist: six==1.16.0
Requires-Dist: sniffio==1.3.1
Requires-Dist: SQLAlchemy==2.0.29
Requires-Dist: starlette==0.37.2
Requires-Dist: secure==0.3.0
Requires-Dist: typing-extensions==4.11.0
Requires-Dist: uvicorn==0.29.0
Requires-Dist: google-api-python-client==2.136.0
Requires-Dist: google-auth==2.31.0
Requires-Dist: google-auth-oauthlib==1.2.0
Requires-Dist: requests-oauthlib==2.0.0
